UR_TCP_RTDE/__init__.py
UR_TCP_RTDE-0.0.1.dist-info/LICENSE
UR_TCP_RTDE-0.0.1.dist-info/METADATA
UR_TCP_RTDE-0.0.1.dist-info/WHEEL
UR_TCP_RTDE-0.0.1.dist-info/top_level.txt
UR_TCP_RTDE-0.0.1.dist-info/RECORD
