Metadata-Version: 2.1
Name: UR-TCP-RTDE
Version: 0.0.1
Summary: UR manipulator communiaction packge.
Home-page: https://github.com/scoard/UR_RTDE
Author: scoard
Author-email: mwangbuaa@126.com
License: UNKNOWN
Platform: UNKNOWN
Classifier: Programming Language :: Python :: 3
Classifier: License :: OSI Approved :: MIT License
Classifier: Operating System :: OS Independent
Requires-Python: >=3.6
